PTO/.DS_Store
PTO/__init__.py
PTO/database/NASA_exoplanet_archive.py
PTO/database/__init__.py
PTO/database/calculation.py
PTO/database/catalog.py
PTO/database/mappers.py
PTO/database/plot.py
PTO/simulations/__init__.py
PTO/simulations/calculations.py
PTO/simulations/plot.py
PTO/simulations/rm_effect.py
PTO/simulations/simulation.ipynb
PTO/simulations/simulator.py
PTO/simulations/spectra_manipulation.py
PTO/spectra_manipulation.py
PTO/telescopes/ETC/ETC_ESPRESSO/A0/0.5arcsec_900s.etc
PTO/telescopes/ETC/ETC_ESPRESSO/A0/0.8arcsec_900s.etc
PTO/telescopes/ETC/ETC_ESPRESSO/A0/1.3arcsec_900s.etc
PTO/telescopes/ETC/ETC_ESPRESSO/A0/info.etc
PTO/telescopes/ETC/ETC_ESPRESSO/A1/0.5arcsec_900s.etc
PTO/telescopes/ETC/ETC_ESPRESSO/A1/0.8arcsec_900s.etc
PTO/telescopes/ETC/ETC_ESPRESSO/A1/1.3arcsec_900s.etc
PTO/telescopes/ETC/ETC_ESPRESSO/A1/info.etc
PTO/telescopes/ETC/ETC_ESPRESSO/B1/0.5arcsec_900s.etc
PTO/telescopes/ETC/ETC_ESPRESSO/B1/0.8arcsec_900s.etc
PTO/telescopes/ETC/ETC_ESPRESSO/B1/1.3arcsec_900s.etc
PTO/telescopes/ETC/ETC_ESPRESSO/B1/info.etc
PTO/telescopes/ETC/ETC_ESPRESSO/B3/0.5arcsec_900s.etc
PTO/telescopes/ETC/ETC_ESPRESSO/B3/0.8arcsec_900s.etc
PTO/telescopes/ETC/ETC_ESPRESSO/B3/1.3arcsec_900s.etc
PTO/telescopes/ETC/ETC_ESPRESSO/B3/info.etc
PTO/telescopes/ETC/ETC_ESPRESSO/B8/0.5arcsec_900s.etc
PTO/telescopes/ETC/ETC_ESPRESSO/B8/0.8arcsec_900s.etc
PTO/telescopes/ETC/ETC_ESPRESSO/B8/1.3arcsec_900s.etc
PTO/telescopes/ETC/ETC_ESPRESSO/B8/info.etc
PTO/telescopes/ETC/ETC_ESPRESSO/B9/0.5arcsec_900s.etc
PTO/telescopes/ETC/ETC_ESPRESSO/B9/0.8arcsec_900s.etc
PTO/telescopes/ETC/ETC_ESPRESSO/B9/1.3arcsec_900s.etc
PTO/telescopes/ETC/ETC_ESPRESSO/B9/info.etc
PTO/telescopes/ETC/ETC_ESPRESSO/F0/0.5arcsec_900s.etc
PTO/telescopes/ETC/ETC_ESPRESSO/F0/0.8arcsec_900s.etc
PTO/telescopes/ETC/ETC_ESPRESSO/F0/1.3arcsec_900s.etc
PTO/telescopes/ETC/ETC_ESPRESSO/F0/info.etc
PTO/telescopes/ETC/ETC_ESPRESSO/G0/0.5arcsec_900s.etc
PTO/telescopes/ETC/ETC_ESPRESSO/G0/0.8arcsec_900s.etc
pto_transits-0.1.8.0.dist-info/LICENSE
pto_transits-0.1.8.0.dist-info/METADATA
pto_transits-0.1.8.0.dist-info/WHEEL
pto_transits-0.1.8.0.dist-info/RECORD
