Metadata-Version: 2.1
Name: pto-transits
Version: 0.1.8.0
Summary: Planner for Transits Observations.
License: GPL-3.0-or-later
Author: Michal Steiner
Author-email: Michal.Steiner@unige.ch
Requires-Python: >=3.10,<4.0
Classifier: License :: OSI Approved :: GNU General Public License v3 or later (GPLv3+)
Classifier: Programming Language :: Python :: 3
Classifier: Programming Language :: Python :: 3.10
Classifier: Programming Language :: Python :: 3.11
Classifier: Programming Language :: Python :: 3.12
Classifier: Programming Language :: Python :: 3.13
Requires-Dist: PyAstronomy
Requires-Dist: astropy
Requires-Dist: calplot
Requires-Dist: colorlog
Requires-Dist: dill
Requires-Dist: expecto
Requires-Dist: matplotlib
Requires-Dist: numpy
Requires-Dist: pandas
Requires-Dist: pyvo
Requires-Dist: seaborn
Requires-Dist: specutils
Requires-Dist: sympy
